expenses_manager/README.md
expenses_manager/__init__.py
expenses_manager/api/__init__.py
expenses_manager/api/main.py
expenses_manager/core/__init__.py
expenses_manager/core/database.py
expenses_manager/core/db_models.py
expenses_manager/core/models.py
expenses_manager/core/repository.py
expenses_manager/core/service.py
2025_assignment2_expenses_manager-0.1.7.dist-info/METADATA
2025_assignment2_expenses_manager-0.1.7.dist-info/WHEEL
2025_assignment2_expenses_manager-0.1.7.dist-info/RECORD
