Metadata-Version: 2.1
Name: 2025_assignment2_expenses_manager
Version: 0.1.7
Summary: Expenses manager application
Author: Lorenzo Barbieri
Requires-Python: >=3.10,<4.0
Classifier: Programming Language :: Python :: 3
Classifier: Programming Language :: Python :: 3.10
Classifier: Programming Language :: Python :: 3.11
Classifier: Programming Language :: Python :: 3.12
Requires-Dist: alembic (>=1.13.0,<2.0.0)
Requires-Dist: fastapi (>=0.121.2,<0.122.0)
Requires-Dist: pydantic (>=2.12.4,<3.0.0)
Requires-Dist: sqlalchemy (>=2.0.23,<3.0.0)
Requires-Dist: uvicorn[standard] (>=0.38.0,<0.39.0)
